django_admin_fk_links/__init__.py
django_admin_fk_links/admin_mixins.py
django_admin_fk_links-0.1.1.dist-info/licenses/LICENSE
django_admin_fk_links-0.1.1.dist-info/METADATA
django_admin_fk_links-0.1.1.dist-info/WHEEL
django_admin_fk_links-0.1.1.dist-info/top_level.txt
django_admin_fk_links-0.1.1.dist-info/RECORD
