Metadata-Version: 2.4
Name: django-admin-fk-links
Version: 0.1.1
Summary: Reusable Django admin mixin that turns ForeignKey fields into direct links to their related admin change views.
Author-email: Rodolfo Valentín Becerra García <rodolvbg@gmail.com>
License: MIT
Project-URL: Repository, https://github.com/rodolvbg/django-admin-fk-links
Project-URL: Homepage, https://github.com/rodolvbg/django-admin-fk-links
Platform: OS Independent
Classifier: Framework :: Django
Classifier: Framework :: Django :: 2.2
Classifier: Framework :: Django :: 3.2
Classifier: Framework :: Django :: 4.2
Classifier: Framework :: Django :: 5.0
Classifier: Framework :: Django :: 6.0
Classifier: Programming Language :: Python :: 3.7
Classifier: Programming Language :: Python :: 3.8
Classifier: Programming Language :: Python :: 3.9
Classifier: Programming Language :: Python :: 3.10
Classifier: Programming Language :: Python :: 3.11
Classifier: Programming Language :: Python :: 3.12
Classifier: Programming Language :: Python :: 3.13
Classifier: Programming Language :: Python :: 3.14
Requires-Python: >=3.7
License-File: LICENSE
Requires-Dist: Django>=2.2
Provides-Extra: tests
Requires-Dist: pytest; extra == "tests"
Requires-Dist: pytest-django; extra == "tests"
Provides-Extra: dev
Requires-Dist: pre-commit; extra == "dev"
Requires-Dist: black; extra == "dev"
Requires-Dist: isort; extra == "dev"
Requires-Dist: ruff; extra == "dev"
Dynamic: license-file
